pyhgvs2/__init__.py
pyhgvs2/constants.py
pyhgvs2/exceptions.py
pyhgvs2/functions.py
pyhgvs2/hgvsg_name.py
pyhgvs2/lookups.py
pyhgvs2/models.py
pyhgvs2/py.typed
pyhgvs2/regex.py
pyhgvs2/utils.py
pyhgvs2/variants.py
pyhgvs2/tests/__init__.py
pyhgvs2/tests/genome.py
pyhgvs2/tests/test_benchmark.py
pyhgvs2/tests/test_hgvs_names.py
pyhgvs2/tests/test_hgvs_names_long.py
pyhgvs2/tests/test_variants.py
pyhgvs2/tests/data/create_benchmark_data.py
pyhgvs2-3.0.4.dist-info/licenses/LICENSE
pyhgvs2-3.0.4.dist-info/METADATA
pyhgvs2-3.0.4.dist-info/WHEEL
pyhgvs2-3.0.4.dist-info/entry_points.txt
pyhgvs2-3.0.4.dist-info/top_level.txt
pyhgvs2-3.0.4.dist-info/RECORD
