Metadata-Version: 2.4
Name: pyhgvs2
Version: 3.0.4
Summary: Fork of pyhgvs
Project-URL: Repository, https://github.com/g-b-f/pyhgvs2
Keywords: hgvs,bioinformatics,genome,variant,DNA,RNA
Requires-Python: >=3.9
License-File: LICENSE
Dynamic: license-file
